odoo/addons/l10n_nl_kvk/README.rst
odoo/addons/l10n_nl_kvk/__init__.py
odoo/addons/l10n_nl_kvk/__manifest__.py
odoo/addons/l10n_nl_kvk/data/api_kvk_nl_bundle.crt
odoo/addons/l10n_nl_kvk/examples/kvk_68727720.json
odoo/addons/l10n_nl_kvk/examples/kvk_69599084.json
odoo/addons/l10n_nl_kvk/examples/kvk_90004760.json
odoo/addons/l10n_nl_kvk/i18n/l10n_nl_kvk.pot
odoo/addons/l10n_nl_kvk/models/__init__.py
odoo/addons/l10n_nl_kvk/models/l10n_nl_kvk_api_handler.py
odoo/addons/l10n_nl_kvk/models/res_config_settings.py
odoo/addons/l10n_nl_kvk/models/res_partner.py
odoo/addons/l10n_nl_kvk/readme/CONFIGURE.rst
odoo/addons/l10n_nl_kvk/readme/CONTRIBUTORS.rst
odoo/addons/l10n_nl_kvk/readme/DESCRIPTION.rst
odoo/addons/l10n_nl_kvk/readme/USAGE.rst
odoo/addons/l10n_nl_kvk/static/description/icon.png
odoo/addons/l10n_nl_kvk/static/description/index.html
odoo/addons/l10n_nl_kvk/tests/__init__.py
odoo/addons/l10n_nl_kvk/tests/test_l10n_nl_kvk.py
odoo/addons/l10n_nl_kvk/tests/test_partner_coc.py
odoo/addons/l10n_nl_kvk/views/res_config_settings.xml
odoo/addons/l10n_nl_kvk/views/res_partner.xml
odoo/addons/l10n_nl_kvk/wizards/__init__.py
odoo/addons/l10n_nl_kvk/wizards/l10n_nl_kvk_preview_wizard.py
odoo/addons/l10n_nl_kvk/wizards/l10n_nl_kvk_preview_wizard.xml
odoo11_addon_l10n_nl_kvk-11.0.1.1.0.dist-info/METADATA
odoo11_addon_l10n_nl_kvk-11.0.1.1.0.dist-info/WHEEL
odoo11_addon_l10n_nl_kvk-11.0.1.1.0.dist-info/top_level.txt
odoo11_addon_l10n_nl_kvk-11.0.1.1.0.dist-info/RECORD
